nrp/__init__.py
nrp/nr.py
nrp-0.0.1.1.dist-info/LICENSE
nrp-0.0.1.1.dist-info/METADATA
nrp-0.0.1.1.dist-info/WHEEL
nrp-0.0.1.1.dist-info/top_level.txt
nrp-0.0.1.1.dist-info/RECORD
