Metadata-Version: 2.1
Name: nrp
Version: 0.0.1.1
Summary: Package for root computation of math functions
Home-page: https://github.com/Shaikh-Ubaid/lpython_packages
Author: Smit Lunagariya
Author-email: smitlunagariya.mat18@itbhu.ac.in
Classifier: Programming Language :: Python :: 3
Classifier: License :: OSI Approved :: MIT License
Classifier: Operating System :: OS Independent
Requires-Python: >=3.6
License-File: LICENSE
Requires-Dist: lpython-emulation
